regexer/__init__.py
regexer/regexer.py
regexer-0.0.2.dist-info/LICENSE
regexer-0.0.2.dist-info/METADATA
regexer-0.0.2.dist-info/WHEEL
regexer-0.0.2.dist-info/top_level.txt
regexer-0.0.2.dist-info/RECORD
