Metadata-Version: 2.1
Name: regexer
Version: 0.0.2
Summary: Simplify work with regex.
Home-page: https://gitlab.com/vladku/regexer
Author: Kurovkyi Vladyslav
License: UNKNOWN
Platform: UNKNOWN
Classifier: Programming Language :: Python :: 3
Classifier: License :: OSI Approved :: MIT License
Classifier: Operating System :: OS Independent
Requires-Python: >=3.6
